{
  "_comment": "Main Sidebar",
  "_version": "6.0.0",
  "_updated": "2026-03-30",
  "categories": [
    {
      "category": null,
      "groups": [
        {
          "group": "Dashboard",
          "icon": "bi-speedometer2",
          "items": [
            {
              "label": "Operational Overview",
              "href": "/v2/dashboard/overview",
              "icon": "bi-graph-up"
            },
            {
              "label": "Attendance & Trends",
              "href": "/v2/dashboard/trends",
              "icon": "bi-bar-chart-line"
            },
            {
              "label": "Safeguarding & Wellbeing",
              "href": "/v2/dashboard/safeguarding",
              "icon": "bi-shield-check"
            }
          ]
        }
      ]
    },
    {
      "category": "PEOPLE",
      "groups": [
        {
          "group": "Students",
          "icon": "bi-mortarboard",
          "items": [
            {
              "label": "All Students",
              "href": "/v2/students",
              "icon": "bi-people"
            },
            {
              "label": "Student Details",
              "href": "/v2/students/details",
              "icon": "bi-person-lines-fill"
            },
            {
              "label": "Add Student",
              "href": "/v2/students/new",
              "icon": "bi-person-plus"
            }
          ]
        },
        {
          "group": "Staff",
          "icon": "bi-person-badge",
          "items": [
            {
              "label": "All Staff",
              "href": "/v2/staff",
              "icon": "bi-people-fill"
            },
            {
              "label": "Staff Details",
              "href": "/v2/staff/details",
              "icon": "bi-person-lines-fill"
            },
            {
              "label": "Add Staff",
              "href": "/v2/staff/new",
              "icon": "bi-person-plus-fill"
            }
          ]
        },
        {
          "group": "Parents",
          "icon": "bi-telephone-inbound",
          "items": []
        }
      ]
    },
    {
      "category": "ACADEMICS",
      "groups": [
        {
          "group": "Classes",
          "icon": "bi-book-fill",
          "items": [
            {
              "label": "All Classes",
              "href": "/v2/classes",
              "icon": "bi-building"
            },
            {
              "label": "Class Details",
              "href": "/v2/classes/details",
              "icon": "bi-card-text"
            },
            {
              "label": "Add Class",
              "href": "/v2/classes/new",
              "icon": "bi-plus-square"
            }
          ]
        }
      ]
    },
    {
      "category": "ATTENDANCE",
      "groups": [
        {
          "group": "Attendance",
          "icon": "bi-calendar-check-fill",
          "items": [
            {
              "label": "All Attendance",
              "href": "/v2/attendance",
              "icon": "bi-calendar-check-fill"
            },
            {
              "label": "Staff Attendance",
              "href": "/v2/attendance/staff",
              "icon": "bi-person-check-fill"
            },
            {
              "label": "Student Attendance",
              "href": "/v2/attendance/student",
              "icon": "bi-mortarboard-fill"
            }
          ]
        }
      ]
    },
    {
      "category": "SYSTEM MANAGEMENT",
      "groups": [
        {
          "group": "User Accounts",
          "icon": "bi-person-gear",
          "flat": true,
          "items": [
            {
              "label": "User Accounts",
              "href": "/v2/users",
              "icon": "bi-person-gear"
            }
          ]
        },
        {
          "group": "Roles & Permissions",
          "icon": "bi-shield-lock",
          "items": [
            {
              "label": "Roles",
              "href": "/v2/system/roles",
              "icon": "bi-shield-lock"
            },
            {
              "label": "Permissions",
              "href": "/v2/system/permissions",
              "icon": "bi-key"
            },
            {
              "label": "Page Access",
              "href": "/v2/system/page-access",
              "icon": "bi-lock"
            }
          ]
        }
      ]
    },
    {
      "category": "CONFIGURATION",
      "groups": [
        {
          "group": "Audit Log",
          "icon": "bi-journal-check",
          "flat": true,
          "items": [
            {
              "label": "Audit Log",
              "href": "/v2/auditlog",
              "icon": "bi-journal-check"
            }
          ]
        }
      ]
    },
    {
      "category": "SETTINGS",
      "groups": [
        {
          "group": "Table Settings",
          "icon": "bi-table",
          "flat": true,
          "items": [
            {
              "label": "Table Settings",
              "href": "/v2/settings",
              "icon": "bi-table"
            }
          ]
        },
        {
          "group": "Diagnostics",
          "icon": "bi-activity",
          "flat": true,
          "items": [
            {
              "label": "Diagnostics",
              "href": "/v2/diagnostics",
              "icon": "bi-activity"
            }
          ]
        },
        {
          "group": "Site",
          "icon": "bi-diagram-3",
          "flat": true,
          "items": [
            {
              "label": "Site",
              "href": "/v2/site",
              "icon": "bi-diagram-3"
            }
          ]
        }
      ]
    },
    {
      "category": "DESIGN SYSTEM",
      "groups": [
        {
          "group": "Global Config",
          "icon": "bi-grid-3x3-gap-fill",
          "flat": true,
          "items": [
            {
              "label": "Global Config",
              "href": "/global-settings/colours",
              "icon": "bi-grid-3x3-gap-fill"
            }
          ]
        }
      ]
    }
  ]
}
